agent_flowpilot/__init__.py
agent_flowpilot/core.py
agent_flowpilot/executor.py
agent_flowpilot/function.py
agent_flowpilot/intent.py
agent_flowpilot/json.py
agent_flowpilot/message.py
agent_flowpilot/models.py
agent_flowpilot/py.typed
agent_flowpilot/scheduler.py
agent_flowpilot/tools.py
agent_flowpilot/validate.py
agent_flowpilot-0.4.3.dist-info/METADATA
agent_flowpilot-0.4.3.dist-info/WHEEL
agent_flowpilot-0.4.3.dist-info/licenses/LICENSE
agent_flowpilot-0.4.3.dist-info/RECORD
